pix_framework/__init__.py
pix_framework/calendar/__init__.py
pix_framework/calendar/availability.py
pix_framework/discovery/__init__.py
pix_framework/discovery/attributes/__init__.py
pix_framework/discovery/attributes/attribute_discovery.py
pix_framework/discovery/attributes/case_attributes.py
pix_framework/discovery/attributes/feature_extraction.py
pix_framework/discovery/attributes/ge_continuous_attributes.py
pix_framework/discovery/attributes/ge_discrete_attributes.py
pix_framework/discovery/attributes/helpers.py
pix_framework/discovery/attributes/metrics.py
pix_framework/discovery/attributes/preprocessing.py
pix_framework/discovery/batch_processing/README.md
pix_framework/discovery/batch_processing/__init__.py
pix_framework/discovery/batch_processing/batch_characteristics.py
pix_framework/discovery/batch_processing/config.py
pix_framework/discovery/batch_processing/discovery.py
pix_framework/discovery/batch_processing/features_table.py
pix_framework/discovery/batch_processing/rules.py
pix_framework/discovery/case_arrival.py
pix_framework/discovery/case_attribute/README.md
pix_framework/discovery/case_attribute/__init__.py
pix_framework/discovery/case_attribute/discovery.py
pix_framework/discovery/gateway_conditions/__init__.py
pix_framework/discovery/gateway_conditions/branching_rules.py
pix_framework/discovery/gateway_conditions/gateway_conditions.py
pix_framework/discovery/gateway_conditions/helpers.py
pix_framework/discovery/gateway_conditions/log_parser.py
pix_framework/discovery/gateway_conditions/preprocessing.py
pix_framework/discovery/gateway_conditions/replayer.py
pix_framework/discovery/gateway_conditions/rules_postprocessing.py
pix_framework/discovery/gateway_conditions/trace_processing.py
pix_framework/discovery/gateway_probabilities.py
pix_framework/discovery/prioritization/README.md
pix_framework/discovery/prioritization/__init__.py
pix_framework/discovery/prioritization/config.py
pix_framework/discovery/prioritization/discovery.py
pix_framework-0.14.2.dist-info/LICENSE
pix_framework-0.14.2.dist-info/METADATA
pix_framework-0.14.2.dist-info/WHEEL
pix_framework-0.14.2.dist-info/RECORD
