Metadata-Version: 2.3
Name: pix-framework
Version: 0.14.2
Summary: Process Improvement Explorer Framework contains process discovery and improvement modules of the Process Improvement Explorer project.
Author: David Chapela de la Campa
Author-email: david.chapela.delacampa@gmail.com
Requires-Python: >=3.9,<3.12
Classifier: Programming Language :: Python :: 3
Classifier: Programming Language :: Python :: 3.9
Classifier: Programming Language :: Python :: 3.10
Classifier: Programming Language :: Python :: 3.11
Requires-Dist: lxml (>=5.3.0,<6.0.0)
Requires-Dist: m5py (>=0.3.3,<0.4.0)
Requires-Dist: networkx (>=3.1,<4.0)
Requires-Dist: optuna (>=4.0.0,<5.0.0)
Requires-Dist: pandas (>=2.2.3,<3.0.0)
Requires-Dist: pandasql (>=0.7.3,<0.8.0)
Requires-Dist: polars (>=1.8.0,<2.0.0)
Requires-Dist: pyarrow (>=17.0.0,<18.0.0)
Requires-Dist: pytz (>=2024.2,<2025.0)
Requires-Dist: scikit-learn (>=1.5.2,<2.0.0)
Requires-Dist: scipy (>=1.13.0,<2.0.0)
Requires-Dist: wittgenstein (>=0.3.4,<0.4.0)
